milvus_filter_expression/__init__.py
milvus_filter_expression/builder.py
milvus_filter_expression/converter.py
milvus_filter_expression/operators.py
milvus_filter_expression/shortcuts.py
milvus_filter_expression-0.1.0.dist-info/METADATA
milvus_filter_expression-0.1.0.dist-info/WHEEL
milvus_filter_expression-0.1.0.dist-info/RECORD
