Metadata-Version: 2.4
Name: milvus-filter-expression
Version: 0.1.0
Summary: Type-safe, MongoDB-style filter builder for Milvus vector database
Project-URL: Homepage, https://github.com/ooeunoo/milvus-filter-expression
Project-URL: Documentation, https://github.com/ooeunoo/milvus-filter-expression#readme
Project-URL: Repository, https://github.com/ooeunoo/milvus-filter-expression
Project-URL: Issues, https://github.com/ooeunoo/milvus-filter-expression/issues
Author-email: ooeunoo <seongeun.cho.dev@gmail.com>
License: MIT
Keywords: filter,milvus,query-builder,vector-database
Classifier: Development Status :: 4 - Beta
Classifier: Intended Audience :: Developers
Classifier: License :: OSI Approved :: MIT License
Classifier: Programming Language :: Python :: 3
Classifier: Programming Language :: Python :: 3.8
Classifier: Programming Language :: Python :: 3.9
Classifier: Programming Language :: Python :: 3.10
Classifier: Programming Language :: Python :: 3.11
Classifier: Programming Language :: Python :: 3.12
Classifier: Topic :: Database
Classifier: Topic :: Software Development :: Libraries :: Python Modules
Requires-Python: >=3.8
Provides-Extra: dev
Requires-Dist: black>=23.0.0; extra == 'dev'
Requires-Dist: mypy>=1.0.0; extra == 'dev'
Requires-Dist: pytest-cov>=4.0.0; extra == 'dev'
Requires-Dist: pytest>=7.0.0; extra == 'dev'
Requires-Dist: ruff>=0.1.0; extra == 'dev'
Provides-Extra: milvus
Requires-Dist: pymilvus>=2.3.0; extra == 'milvus'
